Workbook

Sheet Assumptions
A1: Northwind Robotics — Assumptions
A2: Inputs in blue on yellow; history in blue. USD millions unless stated.
A4: Line item | B4: Unit | C4: 1Q24A | D4: 2Q24A | E4: 3Q24A | F4: 4Q24A | G4: FY24A | H4: 1Q25A | I4: 2Q25A | J4: 3Q25A | K4: 4Q25A | L4: FY25A | M4: 1Q26E | N4: 2Q26E | O4: 3Q26E | P4: 4Q26E | Q4: FY26E | R4: 1Q27E | S4: 2Q27E | T4: 3Q27E | U4: 4Q27E | V4: FY27E
A6: Volume and price
A7: Robots shipped | B7: k | C7: 3.1 | D7: 3.42 | E7: 3.71 | F7: 4.25 | G7: =SUM(C7:F7) | H7: 4.02 | I7: 4.38 | J7: 4.61 | K7: 5.2 | L7: =SUM(H7:K7) | M7: =H7*(1+M8) | N7: =I7*(1+N8) | O7: =J7*(1+O8) | P7: =K7*(1+P8) | Q7: =SUM(M7:P7) | R7: =M7*(1+R8) | S7: =N7*(1+S8) | T7: =O7*(1+T8) | U7: =P7*(1+U8) | V7: =SUM(R7:U7)
A8: Unit growth, year on year | B8: % | M8: 0.22 | N8: 0.22 | O8: 0.22 | P8: 0.22 | R8: 0.18 | S8: 0.18 | T8: 0.18 | U8: 0.18
A9: Average selling price | B9: USD k | C9: 41 | D9: 41.6 | E9: 42.1 | F9: 42.4 | G9: =SUMPRODUCT(C7:F7,C9:F9)/G7 | H9: 43 | I9: 43.3 | J9: 43.9 | K9: 44.6 | L9: =SUMPRODUCT(H7:K7,H9:K9)/L7 | M9: =H9*(1+M10) | N9: =I9*(1+N10) | O9: =J9*(1+O10) | P9: =K9*(1+P10) | Q9: =SUMPRODUCT(M7:P7,M9:P9)/Q7 | R9: =M9*(1+R10) | S9: =N9*(1+S10) | T9: =O9*(1+T10) | U9: =P9*(1+U10) | V9: =SUMPRODUCT(R7:U7,R9:U9)/V7
A10: Price change, year on year | B10: % | M10: 0.03 | N10: 0.03 | O10: 0.03 | P10: 0.03 | R10: 0.02 | S10: 0.02 | T10: 0.02 | U10: 0.02
A12: Margins and costs
A13: Gross margin | B13: % | C13: 0.402 | D13: 0.411 | E13: 0.418 | F13: 0.426 | H13: 0.431 | I13: 0.437 | J13: 0.444 | K13: 0.452 | M13: 0.46 | N13: 0.46 | O13: 0.46 | P13: 0.46 | R13: 0.47 | S13: 0.47 | T13: 0.47 | U13: 0.47
A14: R&D | B14: % rev | C14: 0.14 | D14: 0.14 | E14: 0.14 | F14: 0.14 | H14: 0.14 | I14: 0.14 | J14: 0.14 | K14: 0.14 | M14: 0.135 | N14: 0.135 | O14: 0.135 | P14: 0.135 | R14: 0.135 | S14: 0.135 | T14: 0.135 | U14: 0.135
A15: Sales & marketing | B15: % rev | C15: 0.11 | D15: 0.11 | E15: 0.11 | F15: 0.11 | H15: 0.11 | I15: 0.11 | J15: 0.11 | K15: 0.11 | M15: 0.105 | N15: 0.105 | O15: 0.105 | P15: 0.105 | R15: 0.105 | S15: 0.105 | T15: 0.105 | U15: 0.105
A16: General & administrative | B16: % rev | C16: 0.06 | D16: 0.06 | E16: 0.06 | F16: 0.06 | H16: 0.06 | I16: 0.06 | J16: 0.06 | K16: 0.06 | M16: 0.06 | N16: 0.06 | O16: 0.06 | P16: 0.06 | R16: 0.06 | S16: 0.06 | T16: 0.06 | U16: 0.06
A17: Tax rate | B17: % | C17: 0.21 | D17: 0.21 | E17: 0.21 | F17: 0.21 | H17: 0.21 | I17: 0.21 | J17: 0.21 | K17: 0.21 | M17: 0.21 | N17: 0.21 | O17: 0.21 | P17: 0.21 | R17: 0.21 | S17: 0.21 | T17: 0.21 | U17: 0.21
A19: Capital and working capital
A20: Capital expenditure | B20: % rev | C20: 0.07 | D20: 0.07 | E20: 0.07 | F20: 0.07 | H20: 0.07 | I20: 0.07 | J20: 0.07 | K20: 0.07 | M20: 0.07 | N20: 0.07 | O20: 0.07 | P20: 0.07 | R20: 0.07 | S20: 0.07 | T20: 0.07 | U20: 0.07
A21: Depreciation | B21: % PP&E/qtr | C21: 0.045 | D21: 0.045 | E21: 0.045 | F21: 0.045 | H21: 0.045 | I21: 0.045 | J21: 0.045 | K21: 0.045 | M21: 0.045 | N21: 0.045 | O21: 0.045 | P21: 0.045 | R21: 0.045 | S21: 0.045 | T21: 0.045 | U21: 0.045
A22: Receivable days | B22: days | C22: 52 | D22: 52 | E22: 52 | F22: 52 | H22: 52 | I22: 52 | J22: 52 | K22: 52 | M22: 50 | N22: 50 | O22: 50 | P22: 50 | R22: 50 | S22: 50 | T22: 50 | U22: 50
A23: Payable days | B23: days | C23: 41 | D23: 41 | E23: 41 | F23: 41 | H23: 41 | I23: 41 | J23: 41 | K23: 41 | M23: 41 | N23: 41 | O23: 41 | P23: 41 | R23: 41 | S23: 41 | T23: 41 | U23: 41
A25: Valuation
A26: Cost of capital (WACC) | C26: 0.095
A27: Terminal growth | C27: 0.03
A28: Diluted shares | B28: m | C28: 182

Sheet Income Statement
A1: Northwind Robotics — Income Statement
A2: USD millions. Fiscal year ends 31 December.
A4: Line item | B4: Unit | C4: 1Q24A | D4: 2Q24A | E4: 3Q24A | F4: 4Q24A | G4: FY24A | H4: 1Q25A | I4: 2Q25A | J4: 3Q25A | K4: 4Q25A | L4: FY25A | M4: 1Q26E | N4: 2Q26E | O4: 3Q26E | P4: 4Q26E | Q4: FY26E | R4: 1Q27E | S4: 2Q27E | T4: 3Q27E | U4: 4Q27E | V4: FY27E
A6: Revenue build
A7: Revenue | B7: USDm | C7: =C8 | D7: =D8 | E7: =E8 | F7: =F8 | G7: =SUM(C7:F7) | H7: =H8 | I7: =I8 | J7: =J8 | K7: =K8 | L7: =SUM(H7:K7) | M7: =M8 | N7: =N8 | O7: =O8 | P7: =P8 | Q7: =SUM(M7:P7) | R7: =R8 | S7: =S8 | T7: =T8 | U7: =U8 | V7: =SUM(R7:U7)
A8: Hardware revenue | B8: USDm | C8: ='Assumptions'!C7*'Assumptions'!C9 | D8: ='Assumptions'!D7*'Assumptions'!D9 | E8: ='Assumptions'!E7*'Assumptions'!E9 | F8: ='Assumptions'!F7*'Assumptions'!F9 | G8: =SUM(C8:F8) | H8: ='Assumptions'!H7*'Assumptions'!H9 | I8: ='Assumptions'!I7*'Assumptions'!I9 | J8: ='Assumptions'!J7*'Assumptions'!J9 | K8: ='Assumptions'!K7*'Assumptions'!K9 | L8: =SUM(H8:K8) | M8: ='Assumptions'!M7*'Assumptions'!M9 | N8: ='Assumptions'!N7*'Assumptions'!N9 | O8: ='Assumptions'!O7*'Assumptions'!O9 | P8: ='Assumptions'!P7*'Assumptions'!P9 | Q8: =SUM(M8:P8) | R8: ='Assumptions'!R7*'Assumptions'!R9 | S8: ='Assumptions'!S7*'Assumptions'!S9 | T8: ='Assumptions'!T7*'Assumptions'!T9 | U8: ='Assumptions'!U7*'Assumptions'!U9 | V8: =SUM(R8:U8)
A9: Robots shipped | B9: k | C9: ='Assumptions'!C7 | D9: ='Assumptions'!D7 | E9: ='Assumptions'!E7 | F9: ='Assumptions'!F7 | G9: =SUM(C9:F9) | H9: ='Assumptions'!H7 | I9: ='Assumptions'!I7 | J9: ='Assumptions'!J7 | K9: ='Assumptions'!K7 | L9: =SUM(H9:K9) | M9: ='Assumptions'!M7 | N9: ='Assumptions'!N7 | O9: ='Assumptions'!O7 | P9: ='Assumptions'!P7 | Q9: =SUM(M9:P9) | R9: ='Assumptions'!R7 | S9: ='Assumptions'!S7 | T9: ='Assumptions'!T7 | U9: ='Assumptions'!U7 | V9: =SUM(R9:U9)
A10: Average selling price | B10: USD k | C10: ='Assumptions'!C9 | D10: ='Assumptions'!D9 | E10: ='Assumptions'!E9 | F10: ='Assumptions'!F9 | G10: ='Assumptions'!G9 | H10: ='Assumptions'!H9 | I10: ='Assumptions'!I9 | J10: ='Assumptions'!J9 | ... V10: ='Assumptions'!V9
A11: Revenue growth, year on year | B11: % | H11: =H7/C7-1 | I11: =I7/D7-1 | J11: =J7/E7-1 | K11: =K7/F7-1 | L11: =L7/G7-1 | M11: =M7/H7-1 | N11: =N7/I7-1 | O11: =O7/J7-1 | ... V11: =V7/Q7-1
A13: Profit and loss
A14: Cost of revenue | B14: USDm | C14: =-C7*(1-'Assumptions'!C13) | D14: =-D7*(1-'Assumptions'!D13) | E14: =-E7*(1-'Assumptions'!E13) | F14: =-F7*(1-'Assumptions'!F13) | G14: =SUM(C14:F14) | H14: =-H7*(1-'Assumptions'!H13) | I14: =-I7*(1-'Assumptions'!I13) | J14: =-J7*(1-'Assumptions'!J13) | K14: =-K7*(1-'Assumptions'!K13) | L14: =SUM(H14:K14) | M14: =-M7*(1-'Assumptions'!M13) | N14: =-N7*(1-'Assumptions'!N13) | O14: =-O7*(1-'Assumptions'!O13) | P14: =-P7*(1-'Assumptions'!P13) | Q14: =SUM(M14:P14) | R14: =-R7*(1-'Assumptions'!R13) | S14: =-S7*(1-'Assumptions'!S13) | T14: =-T7*(1-'Assumptions'!T13) | U14: =-U7*(1-'Assumptions'!U13) | V14: =SUM(R14:U14)
A15: Gross profit | B15: USDm | C15: =C7+C14 | D15: =D7+D14 | E15: =E7+E14 | F15: =F7+F14 | G15: =SUM(C15:F15) | H15: =H7+H14 | I15: =I7+I14 | J15: =J7+J14 | K15: =K7+K14 | L15: =SUM(H15:K15) | M15: =M7+M14 | N15: =N7+N14 | O15: =O7+O14 | P15: =P7+P14 | Q15: =SUM(M15:P15) | R15: =R7+R14 | S15: =S7+S14 | T15: =T7+T14 | U15: =U7+U14 | V15: =SUM(R15:U15)
A16: Gross margin | B16: % | C16: =C15/C7 | D16: =D15/D7 | E16: =E15/E7 | F16: =F15/F7 | G16: =G15/G7 | H16: =H15/H7 | I16: =I15/I7 | J16: =J15/J7 | ... V16: =V15/V7
A17: Research & development | B17: USDm | C17: =-C7*'Assumptions'!C14 | D17: =-D7*'Assumptions'!D14 | E17: =-E7*'Assumptions'!E14 | F17: =-F7*'Assumptions'!F14 | G17: =SUM(C17:F17) | H17: =-H7*'Assumptions'!H14 | I17: =-I7*'Assumptions'!I14 | J17: =-J7*'Assumptions'!J14 | K17: =-K7*'Assumptions'!K14 | L17: =SUM(H17:K17) | M17: =-M7*'Assumptions'!M14 | N17: =-N7*'Assumptions'!N14 | O17: =-O7*'Assumptions'!O14 | P17: =-P7*'Assumptions'!P14 | Q17: =SUM(M17:P17) | R17: =-R7*'Assumptions'!R14 | S17: =-S7*'Assumptions'!S14 | T17: =-T7*'Assumptions'!T14 | U17: =-U7*'Assumptions'!U14 | V17: =SUM(R17:U17)
A18: Sales & marketing | B18: USDm | C18: =-C7*'Assumptions'!C15 | D18: =-D7*'Assumptions'!D15 | E18: =-E7*'Assumptions'!E15 | F18: =-F7*'Assumptions'!F15 | G18: =SUM(C18:F18) | H18: =-H7*'Assumptions'!H15 | I18: =-I7*'Assumptions'!I15 | J18: =-J7*'Assumptions'!J15 | K18: =-K7*'Assumptions'!K15 | L18: =SUM(H18:K18) | M18: =-M7*'Assumptions'!M15 | N18: =-N7*'Assumptions'!N15 | O18: =-O7*'Assumptions'!O15 | P18: =-P7*'Assumptions'!P15 | Q18: =SUM(M18:P18) | R18: =-R7*'Assumptions'!R15 | S18: =-S7*'Assumptions'!S15 | T18: =-T7*'Assumptions'!T15 | U18: =-U7*'Assumptions'!U15 | V18: =SUM(R18:U18)
A19: General & administrative | B19: USDm | C19: =-C7*'Assumptions'!C16 | D19: =-D7*'Assumptions'!D16 | E19: =-E7*'Assumptions'!E16 | F19: =-F7*'Assumptions'!F16 | G19: =SUM(C19:F19) | H19: =-H7*'Assumptions'!H16 | I19: =-I7*'Assumptions'!I16 | J19: =-J7*'Assumptions'!J16 | K19: =-K7*'Assumptions'!K16 | L19: =SUM(H19:K19) | M19: =-M7*'Assumptions'!M16 | N19: =-N7*'Assumptions'!N16 | O19: =-O7*'Assumptions'!O16 | P19: =-P7*'Assumptions'!P16 | Q19: =SUM(M19:P19) | R19: =-R7*'Assumptions'!R16 | S19: =-S7*'Assumptions'!S16 | T19: =-T7*'Assumptions'!T16 | U19: =-U7*'Assumptions'!U16 | V19: =SUM(R19:U19)
A20: Operating income | B20: USDm | C20: =C15+SUM(C17:C19) | D20: =D15+SUM(D17:D19) | E20: =E15+SUM(E17:E19) | F20: =F15+SUM(F17:F19) | G20: =SUM(C20:F20) | H20: =H15+SUM(H17:H19) | I20: =I15+SUM(I17:I19) | J20: =J15+SUM(J17:J19) | K20: =K15+SUM(K17:K19) | L20: =SUM(H20:K20) | M20: =M15+SUM(M17:M19) | N20: =N15+SUM(N17:N19) | O20: =O15+SUM(O17:O19) | P20: =P15+SUM(P17:P19) | Q20: =SUM(M20:P20) | R20: =R15+SUM(R17:R19) | S20: =S15+SUM(S17:S19) | T20: =T15+SUM(T17:T19) | U20: =U15+SUM(U17:U19) | V20: =SUM(R20:U20)
A21: Operating margin | B21: % | C21: =C20/C7 | D21: =D20/D7 | E21: =E20/E7 | F21: =F20/F7 | G21: =G20/G7 | H21: =H20/H7 | I21: =I20/I7 | J21: =J20/J7 | ... V21: =V20/V7
A22: Tax | B22: USDm | C22: =-MAX(0,C20)*'Assumptions'!C17 | D22: =-MAX(0,D20)*'Assumptions'!D17 | E22: =-MAX(0,E20)*'Assumptions'!E17 | F22: =-MAX(0,F20)*'Assumptions'!F17 | G22: =SUM(C22:F22) | H22: =-MAX(0,H20)*'Assumptions'!H17 | I22: =-MAX(0,I20)*'Assumptions'!I17 | J22: =-MAX(0,J20)*'Assumptions'!J17 | K22: =-MAX(0,K20)*'Assumptions'!K17 | L22: =SUM(H22:K22) | M22: =-MAX(0,M20)*'Assumptions'!M17 | N22: =-MAX(0,N20)*'Assumptions'!N17 | O22: =-MAX(0,O20)*'Assumptions'!O17 | P22: =-MAX(0,P20)*'Assumptions'!P17 | Q22: =SUM(M22:P22) | R22: =-MAX(0,R20)*'Assumptions'!R17 | S22: =-MAX(0,S20)*'Assumptions'!S17 | T22: =-MAX(0,T20)*'Assumptions'!T17 | U22: =-MAX(0,U20)*'Assumptions'!U17 | V22: =SUM(R22:U22)
A23: Net income | B23: USDm | C23: =C20+C22 | D23: =D20+D22 | E23: =E20+E22 | F23: =F20+F22 | G23: =SUM(C23:F23) | H23: =H20+H22 | I23: =I20+I22 | J23: =J20+J22 | K23: =K20+K22 | L23: =SUM(H23:K23) | M23: =M20+M22 | N23: =N20+N22 | O23: =O20+O22 | P23: =P20+P22 | Q23: =SUM(M23:P23) | R23: =R20+R22 | S23: =S20+S22 | T23: =T20+T22 | U23: =U20+U22 | V23: =SUM(R23:U23)
A24: Earnings per share | B24: USD | C24: =C23/Assumptions!$C$28 | D24: =D23/Assumptions!$C$28 | E24: =E23/Assumptions!$C$28 | F24: =F23/Assumptions!$C$28 | G24: =SUM(C24:F24) | H24: =H23/Assumptions!$C$28 | I24: =I23/Assumptions!$C$28 | J24: =J23/Assumptions!$C$28 | K24: =K23/Assumptions!$C$28 | L24: =SUM(H24:K24) | M24: =M23/Assumptions!$C$28 | N24: =N23/Assumptions!$C$28 | O24: =O23/Assumptions!$C$28 | P24: =P23/Assumptions!$C$28 | Q24: =SUM(M24:P24) | R24: =R23/Assumptions!$C$28 | S24: =S23/Assumptions!$C$28 | T24: =T23/Assumptions!$C$28 | U24: =U23/Assumptions!$C$28 | V24: =SUM(R24:U24)

Sheet Cash Flow
A1: Northwind Robotics — Cash Flow
A2: USD millions.
A4: Line item | B4: Unit | C4: 1Q24A | D4: 2Q24A | E4: 3Q24A | F4: 4Q24A | G4: FY24A | H4: 1Q25A | I4: 2Q25A | J4: 3Q25A | K4: 4Q25A | L4: FY25A | M4: 1Q26E | N4: 2Q26E | O4: 3Q26E | P4: 4Q26E | Q4: FY26E | R4: 1Q27E | S4: 2Q27E | T4: 3Q27E | U4: 4Q27E | V4: FY27E
A6: Operating
A7: Net income | B7: USDm | C7: ='Income Statement'!C23 | D7: ='Income Statement'!D23 | E7: ='Income Statement'!E23 | F7: ='Income Statement'!F23 | G7: =SUM(C7:F7) | H7: ='Income Statement'!H23 | I7: ='Income Statement'!I23 | J7: ='Income Statement'!J23 | K7: ='Income Statement'!K23 | L7: =SUM(H7:K7) | M7: ='Income Statement'!M23 | N7: ='Income Statement'!N23 | O7: ='Income Statement'!O23 | P7: ='Income Statement'!P23 | Q7: =SUM(M7:P7) | R7: ='Income Statement'!R23 | S7: ='Income Statement'!S23 | T7: ='Income Statement'!T23 | U7: ='Income Statement'!U23 | V7: =SUM(R7:U7)
A8: Depreciation | B8: USDm | C8: 9.5 | D8: ='Balance Sheet'!C9*'Assumptions'!D21 | E8: ='Balance Sheet'!D9*'Assumptions'!E21 | F8: ='Balance Sheet'!E9*'Assumptions'!F21 | G8: =SUM(C8:F8) | H8: ='Balance Sheet'!F9*'Assumptions'!H21 | I8: ='Balance Sheet'!H9*'Assumptions'!I21 | J8: ='Balance Sheet'!I9*'Assumptions'!J21 | K8: ='Balance Sheet'!J9*'Assumptions'!K21 | L8: =SUM(H8:K8) | M8: ='Balance Sheet'!K9*'Assumptions'!M21 | N8: ='Balance Sheet'!M9*'Assumptions'!N21 | O8: ='Balance Sheet'!N9*'Assumptions'!O21 | P8: ='Balance Sheet'!O9*'Assumptions'!P21 | Q8: =SUM(M8:P8) | R8: ='Balance Sheet'!P9*'Assumptions'!R21 | S8: ='Balance Sheet'!R9*'Assumptions'!S21 | T8: ='Balance Sheet'!S9*'Assumptions'!T21 | U8: ='Balance Sheet'!T9*'Assumptions'!U21 | V8: =SUM(R8:U8)
A9: Change in working capital | B9: USDm | C9: -4 | D9: =-('Balance Sheet'!D8-'Balance Sheet'!C8)+('Balance Sheet'!D13-'Balance Sheet'!C13) | E9: =-('Balance Sheet'!E8-'Balance Sheet'!D8)+('Balance Sheet'!E13-'Balance Sheet'!D13) | F9: =-('Balance Sheet'!F8-'Balance Sheet'!E8)+('Balance Sheet'!F13-'Balance Sheet'!E13) | G9: =SUM(C9:F9) | H9: =-('Balance Sheet'!H8-'Balance Sheet'!F8)+('Balance Sheet'!H13-'Balance Sheet'!F13) | I9: =-('Balance Sheet'!I8-'Balance Sheet'!H8)+('Balance Sheet'!I13-'Balance Sheet'!H13) | J9: =-('Balance Sheet'!J8-'Balance Sheet'!I8)+('Balance Sheet'!J13-'Balance Sheet'!I13) | K9: =-('Balance Sheet'!K8-'Balance Sheet'!J8)+('Balance Sheet'!K13-'Balance Sheet'!J13) | L9: =SUM(H9:K9) | M9: =-('Balance Sheet'!M8-'Balance Sheet'!K8)+('Balance Sheet'!M13-'Balance Sheet'!K13) | N9: =-('Balance Sheet'!N8-'Balance Sheet'!M8)+('Balance Sheet'!N13-'Balance Sheet'!M13) | O9: =-('Balance Sheet'!O8-'Balance Sheet'!N8)+('Balance Sheet'!O13-'Balance Sheet'!N13) | P9: =-('Balance Sheet'!P8-'Balance Sheet'!O8)+('Balance Sheet'!P13-'Balance Sheet'!O13) | Q9: =SUM(M9:P9) | R9: =-('Balance Sheet'!R8-'Balance Sheet'!P8)+('Balance Sheet'!R13-'Balance Sheet'!P13) | S9: =-('Balance Sheet'!S8-'Balance Sheet'!R8)+('Balance Sheet'!S13-'Balance Sheet'!R13) | T9: =-('Balance Sheet'!T8-'Balance Sheet'!S8)+('Balance Sheet'!T13-'Balance Sheet'!S13) | U9: =-('Balance Sheet'!U8-'Balance Sheet'!T8)+('Balance Sheet'!U13-'Balance Sheet'!T13) | V9: =SUM(R9:U9)
A10: Cash from operations | B10: USDm | C10: =SUM(C7:C9) | D10: =SUM(D7:D9) | E10: =SUM(E7:E9) | F10: =SUM(F7:F9) | G10: =SUM(C10:F10) | H10: =SUM(H7:H9) | I10: =SUM(I7:I9) | J10: =SUM(J7:J9) | K10: =SUM(K7:K9) | L10: =SUM(H10:K10) | M10: =SUM(M7:M9) | N10: =SUM(N7:N9) | O10: =SUM(O7:O9) | P10: =SUM(P7:P9) | Q10: =SUM(M10:P10) | R10: =SUM(R7:R9) | S10: =SUM(S7:S9) | T10: =SUM(T7:T9) | U10: =SUM(U7:U9) | V10: =SUM(R10:U10)
A12: Investing
A13: Capital expenditure | B13: USDm | C13: =-'Income Statement'!C7*'Assumptions'!C20 | D13: =-'Income Statement'!D7*'Assumptions'!D20 | E13: =-'Income Statement'!E7*'Assumptions'!E20 | F13: =-'Income Statement'!F7*'Assumptions'!F20 | G13: =SUM(C13:F13) | H13: =-'Income Statement'!H7*'Assumptions'!H20 | I13: =-'Income Statement'!I7*'Assumptions'!I20 | J13: =-'Income Statement'!J7*'Assumptions'!J20 | K13: =-'Income Statement'!K7*'Assumptions'!K20 | L13: =SUM(H13:K13) | M13: =-'Income Statement'!M7*'Assumptions'!M20 | N13: =-'Income Statement'!N7*'Assumptions'!N20 | O13: =-'Income Statement'!O7*'Assumptions'!O20 | P13: =-'Income Statement'!P7*'Assumptions'!P20 | Q13: =SUM(M13:P13) | R13: =-'Income Statement'!R7*'Assumptions'!R20 | S13: =-'Income Statement'!S7*'Assumptions'!S20 | T13: =-'Income Statement'!T7*'Assumptions'!T20 | U13: =-'Income Statement'!U7*'Assumptions'!U20 | V13: =SUM(R13:U13)
A14: Free cash flow | B14: USDm | C14: =C10+C13 | D14: =D10+D13 | E14: =E10+E13 | F14: =F10+F13 | G14: =SUM(C14:F14) | H14: =H10+H13 | I14: =I10+I13 | J14: =J10+J13 | K14: =K10+K13 | L14: =SUM(H14:K14) | M14: =M10+M13 | N14: =N10+N13 | O14: =O10+O13 | P14: =P10+P13 | Q14: =SUM(M14:P14) | R14: =R10+R13 | S14: =S10+S13 | T14: =T10+T13 | U14: =U10+U13 | V14: =SUM(R14:U14)
A15: Free cash flow margin | B15: % | C15: =C14/'Income Statement'!C7 | D15: =D14/'Income Statement'!D7 | E15: =E14/'Income Statement'!E7 | F15: =F14/'Income Statement'!F7 | G15: =G14/'Income Statement'!G7 | H15: =H14/'Income Statement'!H7 | I15: =I14/'Income Statement'!I7 | J15: =J14/'Income Statement'!J7 | ... V15: =V14/'Income Statement'!V7

Sheet Balance Sheet
A1: Northwind Robotics — Balance Sheet
A2: USD millions, at period end. Annual columns show the year end.
A4: Line item | B4: Unit | C4: 1Q24A | D4: 2Q24A | E4: 3Q24A | F4: 4Q24A | G4: FY24A | H4: 1Q25A | I4: 2Q25A | J4: 3Q25A | K4: 4Q25A | L4: FY25A | M4: 1Q26E | N4: 2Q26E | O4: 3Q26E | P4: 4Q26E | Q4: FY26E | R4: 1Q27E | S4: 2Q27E | T4: 3Q27E | U4: 4Q27E | V4: FY27E
A6: Assets
A7: Cash | B7: USDm | C7: 212 | D7: =C7+'Cash Flow'!D14 | E7: =D7+'Cash Flow'!E14 | F7: =E7+'Cash Flow'!F14 | G7: =F7 | H7: =F7+'Cash Flow'!H14 | I7: =H7+'Cash Flow'!I14 | J7: =I7+'Cash Flow'!J14 | K7: =J7+'Cash Flow'!K14 | L7: =K7 | M7: =K7+'Cash Flow'!M14 | N7: =M7+'Cash Flow'!N14 | O7: =N7+'Cash Flow'!O14 | P7: =O7+'Cash Flow'!P14 | Q7: =P7 | R7: =P7+'Cash Flow'!R14 | S7: =R7+'Cash Flow'!S14 | T7: =S7+'Cash Flow'!T14 | U7: =T7+'Cash Flow'!U14 | V7: =U7
A8: Receivables | B8: USDm | C8: ='Income Statement'!C7*'Assumptions'!C22/91 | D8: ='Income Statement'!D7*'Assumptions'!D22/91 | E8: ='Income Statement'!E7*'Assumptions'!E22/91 | F8: ='Income Statement'!F7*'Assumptions'!F22/91 | G8: =F8 | H8: ='Income Statement'!H7*'Assumptions'!H22/91 | I8: ='Income Statement'!I7*'Assumptions'!I22/91 | J8: ='Income Statement'!J7*'Assumptions'!J22/91 | K8: ='Income Statement'!K7*'Assumptions'!K22/91 | L8: =K8 | M8: ='Income Statement'!M7*'Assumptions'!M22/91 | N8: ='Income Statement'!N7*'Assumptions'!N22/91 | O8: ='Income Statement'!O7*'Assumptions'!O22/91 | P8: ='Income Statement'!P7*'Assumptions'!P22/91 | Q8: =P8 | R8: ='Income Statement'!R7*'Assumptions'!R22/91 | S8: ='Income Statement'!S7*'Assumptions'!S22/91 | T8: ='Income Statement'!T7*'Assumptions'!T22/91 | U8: ='Income Statement'!U7*'Assumptions'!U22/91 | V8: =U8
A9: Property, plant & equipment | B9: USDm | C9: 211 | D9: =C9-'Cash Flow'!D13-'Cash Flow'!D8 | E9: =D9-'Cash Flow'!E13-'Cash Flow'!E8 | F9: =E9-'Cash Flow'!F13-'Cash Flow'!F8 | G9: =F9 | H9: =F9-'Cash Flow'!H13-'Cash Flow'!H8 | I9: =H9-'Cash Flow'!I13-'Cash Flow'!I8 | J9: =I9-'Cash Flow'!J13-'Cash Flow'!J8 | K9: =J9-'Cash Flow'!K13-'Cash Flow'!K8 | L9: =K9 | M9: =K9-'Cash Flow'!M13-'Cash Flow'!M8 | N9: =M9-'Cash Flow'!N13-'Cash Flow'!N8 | O9: =N9-'Cash Flow'!O13-'Cash Flow'!O8 | P9: =O9-'Cash Flow'!P13-'Cash Flow'!P8 | Q9: =P9 | R9: =P9-'Cash Flow'!R13-'Cash Flow'!R8 | S9: =R9-'Cash Flow'!S13-'Cash Flow'!S8 | T9: =S9-'Cash Flow'!T13-'Cash Flow'!T8 | U9: =T9-'Cash Flow'!U13-'Cash Flow'!U8 | V9: =U9
A10: Total assets | B10: USDm | C10: =SUM(C7:C9) | D10: =SUM(D7:D9) | E10: =SUM(E7:E9) | F10: =SUM(F7:F9) | G10: =F10 | H10: =SUM(H7:H9) | I10: =SUM(I7:I9) | J10: =SUM(J7:J9) | K10: =SUM(K7:K9) | L10: =K10 | M10: =SUM(M7:M9) | N10: =SUM(N7:N9) | O10: =SUM(O7:O9) | P10: =SUM(P7:P9) | Q10: =P10 | R10: =SUM(R7:R9) | S10: =SUM(S7:S9) | T10: =SUM(T7:T9) | U10: =SUM(U7:U9) | V10: =U10
A12: Liabilities and equity
A13: Payables | B13: USDm | C13: =-'Income Statement'!C14*'Assumptions'!C23/91 | D13: =-'Income Statement'!D14*'Assumptions'!D23/91 | E13: =-'Income Statement'!E14*'Assumptions'!E23/91 | F13: =-'Income Statement'!F14*'Assumptions'!F23/91 | G13: =F13 | H13: =-'Income Statement'!H14*'Assumptions'!H23/91 | I13: =-'Income Statement'!I14*'Assumptions'!I23/91 | J13: =-'Income Statement'!J14*'Assumptions'!J23/91 | K13: =-'Income Statement'!K14*'Assumptions'!K23/91 | L13: =K13 | M13: =-'Income Statement'!M14*'Assumptions'!M23/91 | N13: =-'Income Statement'!N14*'Assumptions'!N23/91 | O13: =-'Income Statement'!O14*'Assumptions'!O23/91 | P13: =-'Income Statement'!P14*'Assumptions'!P23/91 | Q13: =P13 | R13: =-'Income Statement'!R14*'Assumptions'!R23/91 | S13: =-'Income Statement'!S14*'Assumptions'!S23/91 | T13: =-'Income Statement'!T14*'Assumptions'!T23/91 | U13: =-'Income Statement'!U14*'Assumptions'!U23/91 | V13: =U13
A14: Equity | B14: USDm | C14: =C10-C13 | D14: =D10-D13 | E14: =E10-E13 | F14: =F10-F13 | G14: =F14 | H14: =H10-H13 | I14: =I10-I13 | J14: =J10-J13 | K14: =K10-K13 | L14: =K14 | M14: =M10-M13 | N14: =N10-N13 | O14: =O10-O13 | P14: =P10-P13 | Q14: =P14 | R14: =R10-R13 | S14: =S10-S13 | T14: =T10-T13 | U14: =U10-U13 | V14: =U14
A15: Total liabilities and equity | B15: USDm | C15: =C13+C14 | D15: =D13+D14 | E15: =E13+E14 | F15: =F13+F14 | G15: =F15 | H15: =H13+H14 | I15: =I13+I14 | J15: =J13+J14 | K15: =K13+K14 | L15: =K15 | M15: =M13+M14 | N15: =N13+N14 | O15: =O13+O14 | P15: =P13+P14 | Q15: =P15 | R15: =R13+R14 | S15: =S13+S14 | T15: =T13+T14 | U15: =U13+U14 | V15: =U15

Sheet Valuation
A1: Northwind Robotics — Valuation
A2: Discounted cash flow on the forecast years, terminal value on FY27.
A3: Free cash flow FY26E | B3: ='Cash Flow'!Q14
A4: Free cash flow FY27E | B4: ='Cash Flow'!V14
A5: Cost of capital | B5: =Assumptions!$C$26
A6: Terminal growth | B6: =Assumptions!$C$27
A7: Terminal value | B7: =B4*(1+B6)/(B5-B6)
A8: Enterprise value | B8: =B3/(1+B5)+(B4+B7)/(1+B5)^2
A9: Net cash | B9: ='Balance Sheet'!L7
A10: Equity value | B10: =B8+B9
A11: Diluted shares | B11: =Assumptions!$C$28
A12: Value per share (USD) | B12: =B10/B11
A13: EV / FY26E operating income | B13: =B8/'Income Statement'!Q20

Sheet Checks
A1: Northwind Robotics — Checks
A2: Every check should read zero.
A4: Line item | B4: Unit | C4: 1Q24A | D4: 2Q24A | E4: 3Q24A | F4: 4Q24A | G4: FY24A | H4: 1Q25A | I4: 2Q25A | J4: 3Q25A | K4: 4Q25A | L4: FY25A | M4: 1Q26E | N4: 2Q26E | O4: 3Q26E | P4: 4Q26E | Q4: FY26E | R4: 1Q27E | S4: 2Q27E | T4: 3Q27E | U4: 4Q27E | V4: FY27E
A6: Balance sheet
A7: Assets less liabilities and equity | B7: USDm | C7: ='Balance Sheet'!C10-'Balance Sheet'!C15 | D7: ='Balance Sheet'!D10-'Balance Sheet'!D15 | E7: ='Balance Sheet'!E10-'Balance Sheet'!E15 | F7: ='Balance Sheet'!F10-'Balance Sheet'!F15 | G7: =F7 | H7: ='Balance Sheet'!H10-'Balance Sheet'!H15 | I7: ='Balance Sheet'!I10-'Balance Sheet'!I15 | J7: ='Balance Sheet'!J10-'Balance Sheet'!J15 | K7: ='Balance Sheet'!K10-'Balance Sheet'!K15 | L7: =K7 | M7: ='Balance Sheet'!M10-'Balance Sheet'!M15 | N7: ='Balance Sheet'!N10-'Balance Sheet'!N15 | O7: ='Balance Sheet'!O10-'Balance Sheet'!O15 | P7: ='Balance Sheet'!P10-'Balance Sheet'!P15 | Q7: =P7 | R7: ='Balance Sheet'!R10-'Balance Sheet'!R15 | S7: ='Balance Sheet'!S10-'Balance Sheet'!S15 | T7: ='Balance Sheet'!T10-'Balance Sheet'!T15 | U7: ='Balance Sheet'!U10-'Balance Sheet'!U15 | V7: =U7
